{
  "variantName": "hero-cta",
  "baseBlock": "hero",
  "version": "1.0.0",
  "created": "2026-07-15T12:09:00.000Z",
  "sourceContext": {
    "originUrl": "https://www.omadahealth.com/",
    "originPage": "Omada Health homepage",
    "blockPosition": "bottom"
  },
  "visualCharacteristics": {
    "colorScheme": "dark",
    "density": "spacious",
    "purpose": "cta",
    "imagePattern": "large"
  },
  "contentPattern": {
    "structure": "heading + CTA over full-width dark branded background",
    "buttonCount": 1,
    "imageCount": 1
  },
  "reuseGuidance": {
    "suitableFor": [
      "closing call-to-action bands on a dark branded background",
      "full-width conversion sections with a single CTA"
    ],
    "notSuitableFor": [
      "top-of-page hero banners with video",
      "light-background content sections"
    ]
  },
  "usage": {
    "pagesUsing": ["/index"],
    "reuseCount": 1,
    "lastUsed": "2026-07-15T12:09:00.000Z"
  }
}
